jaclang_streamlit/__init__.py
jaclang_streamlit/commands.py
jaclang_streamlit/dot_viewer.jac
jaclang_streamlit/test_app.jac
jac_streamlit-0.0.6.dist-info/METADATA
jac_streamlit-0.0.6.dist-info/WHEEL
jac_streamlit-0.0.6.dist-info/entry_points.txt
jac_streamlit-0.0.6.dist-info/top_level.txt
jac_streamlit-0.0.6.dist-info/RECORD
