Metadata-Version: 2.4
Name: jac-streamlit
Version: 0.0.6
Summary: Streamlit integration plugin for Jac programming language - enables running and visualizing Jac applications in Streamlit
Author-email: Jason Mars <jason@mars.ninja>
License-Expression: MIT
Project-URL: Repository, https://github.com/jaseci-labs/jaseci
Project-URL: Homepage, https://jac-lang.org
Project-URL: Documentation, https://jac-lang.org
Keywords: jac,jaclang,jaseci,streamlit,visualization,graph,object-spatial
Requires-Python: >=3.12
Requires-Dist: jaclang>=0.9.6
Requires-Dist: streamlit>=1.38.0
Requires-Dist: pydot>=3.0.1
Requires-Dist: streamlit-agraph>=0.0.45
